Metadata-Version: 2.1
Name: tikzplotlib
Version: 0.10.0
Summary: Convert matplotlib figures into TikZ/PGFPlots
Keywords: latex,tikz,matplotlib,graphics
Author-email: Nico Schlömer <nico.schloemer@gmail.com>
Requires-Python: >=3.7
Classifier: Development Status :: 5 - Production/Stable
Classifier: Framework :: Matplotlib
Classifier: License :: OSI Approved :: MIT License
Classifier: Operating System :: OS Independent
Classifier: Programming Language :: Python
Classifier: Programming Language :: Python :: 3
Classifier: Programming Language :: Python :: 3.7
Classifier: Programming Language :: Python :: 3.8
Classifier: Programming Language :: Python :: 3.9
Classifier: Programming Language :: Python :: 3.10
Classifier: Topic :: Multimedia :: Graphics :: Graphics Conversion
Classifier: Topic :: Scientific/Engineering :: Visualization
Requires-Dist: matplotlib >= 1.4.0
Requires-Dist: numpy
Requires-Dist: Pillow
Requires-Dist: webcolors
Project-URL: Code, https://github.com/nschloe/tikzplotlib
Project-URL: Funding, https://github.com/sponsors/nschloe
Project-URL: Issues, https://github.com/nschloe/tikzplotlib/issues
